main.py
test_pkg/__init__.py
zitan/__init__.py
zitan-0.1.3.dist-info/LICENSE.txt
zitan-0.1.3.dist-info/METADATA
zitan-0.1.3.dist-info/WHEEL
zitan-0.1.3.dist-info/top_level.txt
zitan-0.1.3.dist-info/RECORD
